MANIFEST.in
setup.cfg
setup.py
InfusionSoft_API.egg-info/PKG-INFO
InfusionSoft_API.egg-info/SOURCES.txt
InfusionSoft_API.egg-info/dependency_links.txt
InfusionSoft_API.egg-info/pbr.json
InfusionSoft_API.egg-info/top_level.txt
infusionsoft/__init__.py
infusionsoft/library.py