Metadata-Version: 1.0
Name: InfusionSoft-API
Version: 0.1.1
Summary: python wrapper for InfusionSoft API
Home-page: https://github.com/infusionsoft/Official-API-Python-Library
Author: Nick Sloan
Author-email: spam+pypi@nasloan.com
License: UNKNOWN
Platform: UNKNOWN
